logsweet/__init__.py
logsweet/actions.py
logsweet/cli.py
logsweet/colors.py
logsweet/config.py
logsweet/core.py
logsweet/mock.py
logsweet/net.py
logsweet/signals.py
logsweet/watch.py
logsweet/test/__init__.py
logsweet/test/test_core.py
logsweet/test/test_watch.py
logsweet-0.1.0.dist-info/LICENSE
logsweet-0.1.0.dist-info/METADATA
logsweet-0.1.0.dist-info/WHEEL
logsweet-0.1.0.dist-info/entry_points.txt
logsweet-0.1.0.dist-info/top_level.txt
logsweet-0.1.0.dist-info/RECORD
