Metadata-Version: 2.1
Name: logsweet
Version: 0.1.0
Summary: Broadcast and receive log messages over network.
Home-page: https://github.com/mastersign/logsweet
Author: Tobias Kiertscher
Author-email: dev@mastersign.de
Maintainer: Tobias Kiertscher
Maintainer-email: dev@mastersign.de
License: BSD-3
Keywords: lib logsweet
Platform: UNKNOWN
Classifier: Development Status :: 3 - Alpha
Classifier: License :: OSI Approved :: BSD License
Classifier: Natural Language :: English
Classifier: Operating System :: OS Independent
Classifier: Programming Language :: Python
Classifier: Programming Language :: Python :: 3
Classifier: Programming Language :: Python :: 3.4
Classifier: Programming Language :: Python :: 3.5
Classifier: Programming Language :: Python :: 3.6
Classifier: Programming Language :: Python :: 3.7
Requires-Dist: click (>=6)
Requires-Dist: pyzmq (>=16)
Requires-Dist: PyYAML (>=3)
Requires-Dist: colorful (<1,>=0.5)
Requires-Dist: requests-futures (<1,>=0.9)
